{"name":"富江","nameCn":"","cover":"//lain.bgm.tv/pic/crt/m/5f/c7/11255_crt_V8OGL.jpg","info":"<li><span>别名: </span>川上富江</li><li><span style=\"visibility:hidden;\">别名: </span>かわかみ とみえ</li><li><span style=\"visibility:hidden;\">别名: </span>Kawakami Tomie</li><li><span>性别: </span>女</li><li><span>引用来源: </span>Wikipedia</li>","detail":"富江是由漫画家伊藤润二所创造的一名漫画人物。之后也发展出电影系列。<br /><br />作为伊藤润二的第一部作品。富江于1986年拿到恐怖漫画奖项“梅图赏”佳作，于1987年刊载于万圣节月刊。这是伊藤润二的成名之作。此后伊藤润二又创作了“富江 森田病院篇”，“富江 PART 2”。<br /><br />在漫画故事中，川上富江美丽的外表有一股魔力，会让男性们陷入疯狂迷恋。男性为了亲近富江，会不择手段的讨好其骄纵残忍的个性。而在与富江交往后又会因强烈的忌妒、恨意与莫明的杀意残杀富江，把富江肢解。但富江事实上是不老不死的妖怪，一块尸块、一处血迹甚至少数细胞都可以再生成一个富江。富江之间也会互相残杀。数量不明的富江以残害男女为乐已有上百年的历史。富江对女性也带来各种威胁。为富江疯狂的男性会伤害其他女性，甚至富江本身的细胞也会侵蚀其他女性使其变成富江。在“富江 PART 2”之中，也有女性保母为婴儿富江疯狂的情节。","jobs":[{"href":"/subject/12057","name":"富江 PARTIII","nameCn":"富江 PART3","cover":"//lain.bgm.tv/pic/cover/g/8b/91/12057_jp.jpg","staff":"主角","cast":"","castHref":"","castTag":"","castCover":""},{"href":"/subject/4319","name":"伊藤潤二恐怖マンガCollection (2)","nameCn":"","cover":"//lain.bgm.tv/pic/cover/g/8e/1a/4319_lO02j.jpg","staff":"主角","cast":"","castHref":"","castTag":"","castCover":""},{"href":"/subject/4318","name":"伊藤潤二恐怖マンガCollection (1)","nameCn":"","cover":"//lain.bgm.tv/pic/cover/g/4b/85/135381_Nr3td.jpg","staff":"主角","cast":"","castHref":"","castTag":"","castCover":""},{"href":"/subject/4317","name":"伊藤潤二恐怖マンガCollection","nameCn":"伊藤润二恐怖漫画精选","cover":"//lain.bgm.tv/pic/cover/g/d2/90/4317_3R4Xs.jpg","staff":"主角","cast":"","castHref":"","castTag":"","castCover":""},{"href":"/subject/13147","name":"富江－The complete comics of Tomie","nameCn":"富江","cover":"//lain.bgm.tv/pic/cover/g/39/5d/13147_jp.jpg","staff":"主角","cast":"","castHref":"","castTag":"","castCover":""},{"href":"/subject/218453","name":"伊藤潤二『コレクション』","nameCn":"伊藤润二惊选集","cover":"//lain.bgm.tv/pic/cover/g/19/b9/218453_Py4pH.jpg","staff":"主角","cast":"末柄里恵","castHref":"/person/12356","castTag":"CV","castCover":"//lain.bgm.tv/pic/crt/s/17/28/12356_prsn_xZ0xx.jpg"}]}