{"name":"ニュートン","nameCn":"牛顿","cover":"//lain.bgm.tv/pic/crt/m/52/c9/78632_crt_82K6C.jpg","info":"<li><span>简体中文名: </span>牛顿</li><li><span>别名: </span>Newton</li><li><span>性别: </span>男</li>","detail":"ガリハバラでリンゴを売っているイケメン。リンゴへの愛情は不滅で、赤く丸い果物を手に持って、じっと眺めていることが多い。実は自分が「万有魅力」を持っていると勘いしているナルシストで、しょっちゅう女性たちから追いかけられているが、いまだにリンゴの他には興味が持てないらしい。","jobs":[{"href":"/subject/4557","name":"マリー＆ガリー 2.0","nameCn":"玛丽与伽利 ver 2.0","cover":"//lain.bgm.tv/pic/cover/g/35/96/4557_Zv0Vv.jpg","staff":"配角","cast":"阪田智靖","castHref":"/person/39018","castTag":"CV","castCover":"//lain.bgm.tv/pic/crt/s/22/f7/39018_prsn_2p222.jpg","type":2},{"href":"/subject/4556","name":"マリー＆ガリー","nameCn":"玛丽&amp;伽利","cover":"//lain.bgm.tv/pic/cover/g/6f/51/4556_20l5z.jpg","staff":"配角","cast":"阪田智靖","castHref":"/person/39018","castTag":"CV","castCover":"//lain.bgm.tv/pic/crt/s/22/f7/39018_prsn_2p222.jpg","type":2}]}