{"name":"ゆきゆきえ","nameCn":"","cover":"","info":"<li><span>性别: </span>女</li>","detail":"美术监督行信三之妻，二人常合作参与东映动画少女向作品。《小魔女DOREMI》系列后休职，2011年在《食梦者玛莉》中复出。","works":[{"href":"/subject/278898","name":"魔女見習いをさがして / 寻找见习魔女","cover":"//lain.bgm.tv/pic/cover/g/dc/c7/278898_AzLA1.jpg","staff":"美术设计"},{"href":"/subject/129384","name":"ワカコ酒 / 和歌子酒","cover":"//lain.bgm.tv/pic/cover/g/74/4d/129384_vd3ir.jpg","staff":"美术监督"},{"href":"/subject/66375","name":"ノ・ゾ・キ・ア・ナ / 偷·窥·的·小·洞","cover":"/img/no_icon_subject.png","staff":"美术监督"},{"href":"/subject/8990","name":"夢喰いメリー / 食梦者玛利","cover":"//lain.bgm.tv/pic/cover/g/ce/65/8990_wRk3u.jpg","staff":"美术监督"},{"href":"/subject/9564","name":"明日のナージャ / 明日的娜嘉","cover":"//lain.bgm.tv/pic/cover/g/a3/b3/9564_zTwcb.jpg","staff":"美术设计"}]}