{"name":"樫原紗理奈","nameCn":"樫原纱理奈","cover":"//lain.bgm.tv/pic/crt/m/fc/ed/36610_crt_3KN1D.jpg","info":"<li><span>简体中文名: </span>樫原纱理奈</li><li><span>别名: </span>Sarina Kashiwara</li><li><span style=\"visibility:hidden;\">别名: </span>かしわら さりな</li><li><span>性别: </span>女</li><li><span>身高: </span>157cm</li><li><span>BWH: </span>90/53/91</li><li><span>最喜欢的乐队: </span>The Clash、Red Hot Chili Peppers</li>","detail":"吉他手。出身历史悠久的资本家家庭，其家庭对学校也做了很多赞助。<br />由于体弱多病加上祖父管教严厉，在学校内交际面比较窄。<br />大小姐风格，言谈优雅，性格稳重。不过也有内心坚强的一面。<br />同绮良里很要好，事情一旦涉及到绮良里，就会挺身而出。","jobs":[{"href":"/subject/2723","name":"キラ☆キラ","nameCn":"KIRA☆KIRA 煌煌舞台","cover":"//lain.bgm.tv/pic/cover/g/c3/15/2723_RWt07.jpg","staff":"主角","cast":"小島めぐみ","castHref":"/person/15107","castTag":"CV","castCover":"//lain.bgm.tv/pic/crt/s/f4/bd/15107_prsn_7s4d8.jpg"}]}