{"name":"デッドボールP","nameCn":"竹下遼","cover":"//lain.bgm.tv/pic/crt/m/3e/bd/8802_prsn_22jHJ.jpg","info":"<li><span>简体中文名: </span>竹下遼</li><li><span>别名: </span>槇タケポン</li><li><span style=\"visibility:hidden;\">别名: </span>Deadball-P</li><li><span style=\"visibility:hidden;\">别名: </span>Deadball P</li><li><span style=\"visibility:hidden;\">别名: </span>DeadballP</li><li><span style=\"visibility:hidden;\">别名: </span>デッドボールP</li><li><span style=\"visibility:hidden;\">别名: </span>Dead Ball P</li><li><span style=\"visibility:hidden;\">别名: </span>槇 タケポン</li><li><span style=\"visibility:hidden;\">别名: </span>Takepon Maki</li><li><span style=\"visibility:hidden;\">别名: </span>Dead Ball</li><li><span style=\"visibility:hidden;\">别名: </span>たけした りょう</li><li><span style=\"visibility:hidden;\">别名: </span>Ryo Takeshita</li><li><span style=\"visibility:hidden;\">别名: </span>死球P</li><li><span>性别: </span>男</li><li><span>生日: </span>1985-02-23</li><li><span>出身地: </span>Kanagawa, Japan</li><li><span>Twitter: </span>@deadballp</li>","detail":"デッドボールPは、Vocaloidシリーズを用いて楽曲を発表している制作者である。（作詞・作曲、およびVocaloid歌唱データ作成をすべて行っている。）略称は「デP」。同人音楽サークル「5/4 TAKEPOD」では「槇タケポン」の名で活動している。<br /><br />ニコニコ動画では「デッドボールP」として定着しており、以前からの名前である「槇タケポン」の名で呼ぶ者は少ないが、リアルでは後者の名前で呼ばれた方がうれしいようだ。<br /><br />Vocaloid動画作成者としてのデビューは、2007年09月27日の「初音ミクのちょっとHなオリジナル曲1 既成事実 -暫定版-」（sm1155685・削除済み）。当時は「アウト」「直球過ぎる」「セウト」などのコメントが多かったが、10/13 15:08に「直球というよりデッドボール」というコメントがあったことから、「デッドボールP」という呼び名が定着した。<br /><br />その後「ちょっとHな～」シリーズや「永久に続く五線譜」「金の聖夜霜雪に朽ちて」などの楽曲を公開するが、週刊VOCALOIDランキングではかなりの割合で「大人の事情による除外」を受けており、「除外王」の称号を得た。また、その歌詞の内容から恥ずかしい歌詞三大Pの一人に数えられている。<br /><br />2008年1月17日にクリプトン社から「ちょっとHな～」シリーズの一部楽曲を権利者削除（利用規約違反）された際には大きな波紋を呼んだが、氏が権利者削除を受け入れる旨のコメントを発表したことで問題は収束した。<br /><br />その後、削除された楽曲は問題点修正された「修正版（ちょっとアレな曲～）」が公開されている。一部ではどこが変わったのか分からないと言われているがちゃんと変わっている。<br /><br />自分の楽曲を用いた「歌ってみた」「演奏してみた」等の動画をこまめにチェックすることに定評があり、作者コメント欄に「支援」リンクを張ることで知られている。詳細は「デP巡回済」を参照。初期はほぼ全ての関連動画をコメント欄に書いていたが、人気作では表記しきれなくなり特に気に入った作品(?)を記入するようになっているようだ。<br /><br />この発見速度には定評があったが「今までの速度が異常で、今後は普通の速度になるけどよろしく」という旨のコメントを記している。<br /><br />その頃からか、あまりにもどうしようもない動画など場合、自分の関連曲であってもスルーする事が増えているようだ。単に関連動画の数が増えすぎたためかもしれない。<br /><br />動画視聴者との距離感が非常に近く、「既成事実 -Full Ver.-（旧版）」の10万再生記念に「続・既成事実（旧版）」を作成したり、「既成事実（修正版）」の10万再生記念に「真・既成事実」を作成したりするなどしている。（「続・既成事実」は10万再生の当日中に、「真・既成事実」は10万再生の翌日に新曲をアップしている。）<br /><br />再生数と比較して「演奏してみた」系統の動画や、そのセッション動画が多めなのも特徴。代表的なのは多数のセッションが発生した「曾根崎心中」だが、それ以外にも「牛乳飲め！」「Wash My Blood」など、演奏者への挑戦状のような状況の曲も少なくないため、演奏レベルが高くなる傾向にある。演奏者は[TEST]、萌作、酪農仮面、紅い流星、哲犬など。<br /><br />デP本人も、関連曲・オリジナルを「演奏してみた」「歌ってみた」などの動画を投稿している。","works":[{"href":"/subject/287132","name":"タマユラミライ オリジナルサウンドトラック","cover":"//lain.bgm.tv/pic/cover/g/6e/a6/287132_122o2.jpg","staff":"作曲"},{"href":"/subject/255032","name":"タマユラミライ","cover":"//lain.bgm.tv/pic/cover/g/15/2f/255032_38Z3c.jpg","staff":"主题歌作曲"},{"href":"/subject/283616","name":"タマユラミライ SPECIAL SOUNDTRACK","cover":"//lain.bgm.tv/pic/cover/g/d5/40/283616_736N1.jpg","staff":"作曲"}]}