{"name":"コミック アース・スター","nameCn":"","cover":"//lain.bgm.tv/pic/crt/m/eb/eb/8418_prsn_E70M3.jpg","info":"<li><span>别名: </span>コミックアース・スター</li><li><span style=\"visibility:hidden;\">别名: </span>COMIC EARTH STAR</li><li><span style=\"visibility:hidden;\">别名: </span>コミックアーススター</li><li><span style=\"visibility:hidden;\">别名: </span>アーススター</li><li><span style=\"visibility:hidden;\">别名: </span>月刊コミック アース・スター</li><li><span style=\"visibility:hidden;\">别名: </span>月刊コミックアース☆スター</li><li><span>生日: </span>2011年3月12日</li><li><span>HP: </span>http://comic-earthstar.jp/</li><li><span>Twitter: </span>@comicearthstar</li>","detail":"アース・スター エンターテイメントが発行する日本の漫画雑誌。2011年3月12日創刊。<br /><br />2014年11月12日（2014年12月号）纸媒体休刊<br /><br />2015年1月19日数字版创刊，转为WEB杂志","works":[{"href":"/subject/265654","name":"最強呪族転生 ～魔術オタクの理想郷～ / 最强咒族转生～一个天才魔术师的惬意生活～","cover":"//lain.bgm.tv/pic/cover/g/a8/03/265654_sWs8S.jpg","staff":"连载杂志"},{"href":"/subject/226245","name":"死神の女王と冥府の番犬","cover":"//lain.bgm.tv/pic/cover/g/92/fc/226245_55G5e.jpg","staff":"连载杂志"},{"href":"/subject/220773","name":"野生のラスボスが現れた！ 黒翼の覇王 / 野生的最终BOSS出现了！","cover":"//lain.bgm.tv/pic/cover/g/2c/26/220773_Pi9kp.jpg","staff":"连载杂志"},{"href":"/subject/242602","name":"戦国小町苦労譚","cover":"//lain.bgm.tv/pic/cover/g/c3/bc/242602_8O3p3.jpg","staff":"连载杂志"},{"href":"/subject/236061","name":"悠久の愚者アズリーの、 賢者のすゝめ―と、ポチの大冒険― / 悠久愚者阿兹利的贤者之道","cover":"//lain.bgm.tv/pic/cover/g/4f/15/236061_fuzy1.jpg","staff":"连载杂志"}]}