{"name":"トチローの母","nameCn":"","cover":"//lain.bgm.tv/pic/crt/m/b8/f3/9850_crt_anidb.jpg","info":"<li><span>性别: </span>女</li><li><span>别名: </span>Tochirou no Haha</li><li><span style=\"visibility:hidden;\">别名: </span>トチローの母</li><li><span>引用来源: </span>anidb.net</li>","detail":"","jobs":[{"href":"/subject/23307","name":"銀河鉄道999 映画版","nameCn":"银河铁道999 剧场版","cover":"//lain.bgm.tv/pic/cover/g/0b/51/23307_l67OO.jpg","staff":"配角","cast":"麻生美代子","castHref":"/person/4366","castTag":"CV","castCover":"//lain.bgm.tv/pic/crt/s/db/20/4366_seiyu_anidb.jpg","type":2}]}