{"name":"足立友","nameCn":"足立友","cover":"//lain.bgm.tv/pic/crt/m/5c/91/4858_prsn_SYZBA.jpg","info":"<li><span>简体中文名: </span>足立友</li><li><span>别名: </span>足立友 ＝ こいでりこ ＝ 柴田蕗</li><li><span style=\"visibility:hidden;\">别名: </span>足立友</li><li><span style=\"visibility:hidden;\">别名: </span>あだち とも</li><li><span style=\"visibility:hidden;\">别名: </span>Adachi Tomo</li><li><span>性别: </span>女</li><li><span>生日: </span>1980-04-27</li><li><span>引用来源: </span>anidb.net</li>","detail":"","voices":[{"href":"/character/58993","name":"守崎美紅","nameCn":"","cover":"//lain.bgm.tv/pic/crt/s/8a/0f/58993_crt_2zrP3.jpg","subjectHref":"/subject/229685","subjectName":"人妻戦隊アイサイガーFLASH","subjectNameCn":"","staff":"主角","subjectCover":"//lain.bgm.tv/pic/cover/g/29/c2/229685_3zuNt.jpg"},{"href":"/character/56743","name":"浅倉 香澄","nameCn":"","cover":"//lain.bgm.tv/pic/crt/s/63/f5/56743_crt_XVi60.jpg","subjectHref":"/subject/152367","subjectName":"BIN★CANダーリン","subjectNameCn":"","staff":"主角","subjectCover":"//lain.bgm.tv/pic/cover/g/b6/b5/152367_3sstW.jpg"},{"href":"/character/53379","name":"武中つかさ","nameCn":"","cover":"//lain.bgm.tv/pic/crt/s/b0/9d/53379_crt_mBOet.jpg","subjectHref":"/subject/99099","subjectName":"真説 猟奇の檻","subjectNameCn":"真说 猎奇之槛","staff":"主角","subjectCover":"//lain.bgm.tv/pic/cover/g/d0/a1/99099_7mCwW.jpg"}],"works":[{"href":"/subject/142364","name":"Only One / Only Love","cover":"//lain.bgm.tv/pic/cover/g/37/e9/142364_ofnx8.jpg","staff":"艺术家"},{"href":"/subject/142357","name":"HoneyComing First Impression“YUMA ism”","cover":"//lain.bgm.tv/pic/cover/g/85/a3/142357_863gL.jpg","staff":"艺术家"}]}