{"name":"五十嵐望","nameCn":"五十岚望","cover":"//lain.bgm.tv/pic/crt/m/0e/b4/52223_crt_7x6Y6.jpg","info":"<li><span>简体中文名: </span>五十岚望</li><li><span>别名: </span>いがらしのぞむ</li><li><span>性别: </span>男</li>","detail":"","jobs":[{"href":"/subject/169274","name":"アイカツスターズ!","nameCn":"偶像活动Stars","cover":"//lain.bgm.tv/pic/cover/g/29/6e/169274_45Kit.jpg","staff":"配角","cast":"上村祐翔","castHref":"/person/13932","castTag":"CV","castCover":"//lain.bgm.tv/pic/crt/s/55/d3/13932_prsn_Lxru8.jpg"},{"href":"/subject/207491","name":"アイカツスターズ! 2年目","nameCn":"偶像活动Stars 第二年","cover":"//lain.bgm.tv/pic/cover/g/27/ef/207491_Oih75.jpg","staff":"客串","cast":"上村祐翔","castHref":"/person/13932","castTag":"CV","castCover":"//lain.bgm.tv/pic/crt/s/55/d3/13932_prsn_Lxru8.jpg"}]}