{"name":"ホームズ","nameCn":"福尔摩斯","cover":"//lain.bgm.tv/pic/crt/m/9a/2b/31579_crt_a5UzA.jpg","info":"<li><span>简体中文名: </span>福尔摩斯</li><li><span>别名: </span>Holmes</li>","detail":"在伦敦做侦探。充满谜团的青年。<br />不去解谜。不去推理。新种的迷侦探。<br />但，被委托的内容不知不觉间就会解决掉，<br />身为一名侦探评价相当高。<br />暗中从伦敦市警那里接受了搜索吸血鬼的任务。<br />虽然带着手枪，但里面只有一发子弹。<br />讨厌喧闹。白天会很爱困。不喜欢和人交流。不喜欢做麻烦的事。<br />如此这般，只是一味过着怠惰的生活。","jobs":[{"href":"/subject/120703","name":"VAMPIRE HOLMES","nameCn":"吸血鬼福尔摩斯","cover":"//lain.bgm.tv/pic/cover/g/7a/da/120703_0ih7t.jpg","staff":"主角","cast":"瀬名快伸","castHref":"/person/18136","castTag":"CV","castCover":"//lain.bgm.tv/pic/crt/s/c2/26/18136_prsn_uogr4.jpg"}]}