{"name":"クリスティン・ケトラ","nameCn":"","cover":"//lain.bgm.tv/pic/crt/m/a1/63/58129_crt_s555s.jpg","info":"<li><span>性别: </span>女</li><li><span>生日: </span>9月3日</li><li><span>身高: </span>158cm</li><li><span>BWH: </span>82(C)/56/82</li>","detail":"神聖魔術を操る聖神官で、品行方正な優等生。聖樹教会の教義では冥王を邪神と定めていることから、冥王に一目惚れしてしまった自分を戒めるため毎晩滝に打たれ「へあっ！ へあっ！」と聖印を切っている。<br /><br />種族：人間<br /><br />ステータス<br />聖神官が自らの信念と祈りを解き放ったとき、崇高なる奇跡が起きるといいます。<br />アイリス随一の癒し手として、戦列を支え活躍することでしょう。<br /><br />来歴<br />聖職者としての才能を見いだされ、聖樹教会法皇領にある修道院で修行に励んでいた。<br /><br />趣味・特技<br />修道院の院長直伝の竪琴が趣味。曲調はゆったりしており、聞く者を眠りへ誘う。<br />修道院で花畑の管理を任され、新しい花の色を作ることに没頭。人気のある新しい花を生み出し、修道院は潤った。その花にはクリスの名前が付けられている。<br /><br />好きなもの・こと<br />修道院ではなかなか口にできなかったため、甘いお菓子に目がない。<br />お菓子目当てに、ついついパトリシアと修道院を抜け出したこともある。<br /><br />苦手なもの・こと<br />とにかく男子に慣れておらず、ちょっと身体が触れただけで真っ赤になってしまう。","jobs":[{"href":"/subject/226257","name":"あいりすミスティリア！～少女のつむぐ夢の秘跡～","nameCn":"","cover":"//lain.bgm.tv/pic/cover/g/bf/9b/226257_fPFkf.jpg","staff":"主角","cast":"種﨑敦美","castHref":"/person/7575","castTag":"CV","castCover":"//lain.bgm.tv/pic/crt/s/7a/a7/7575_prsn_qDEyy.jpg"}]}