{"name":"大石まさる","nameCn":"大石胜","cover":"","info":"<li><span>简体中文名: </span>大石胜</li><li><span>别名: </span>夢ノ二</li><li><span style=\"visibility:hidden;\">别名: </span>おおいし まさる</li><li><span>生日: </span>1972年10月16日</li>","detail":"日本の漫画家。東京都出身。<br />『コミックウインクル』（海王社）に掲載された『火星探掘紀行』でデビュー。<br />1998年以降は主に少年画報社の漫画雑誌で作品を発表している。<br />漫画家の柳沼行とは中学時代の同級生で、現在も交流がある。","works":[{"href":"/subject/167985","name":"キラリティ","cover":"//lain.bgm.tv/pic/cover/g/d8/25/167985_jp.jpg","staff":"作者"},{"href":"/subject/167981","name":"稲田小鬼物語 / 稻田小鬼物语","cover":"//lain.bgm.tv/pic/cover/g/eb/d8/167981_jp.jpg","staff":"作者"},{"href":"/subject/41146","name":"水惑星年代記 / 水惑星年代记","cover":"//lain.bgm.tv/pic/cover/g/bd/08/41146_AwqEe.jpg","staff":"作者"},{"href":"/subject/46786","name":"空からこぼれた物語","cover":"//lain.bgm.tv/pic/cover/g/9e/1b/46786_jp.jpg","staff":"作者"},{"href":"/subject/46311","name":"みずいろ / 水色的青春","cover":"//lain.bgm.tv/pic/cover/g/7a/04/46311_dJcfj.jpg","staff":"作者"}]}