{"name":"根岸まさ子","nameCn":"根岸真子","cover":"//lain.bgm.tv/pic/crt/m/0a/d9/35543_crt_ywYn9.jpg","info":"<li><span>简体中文名: </span>根岸真子</li><li><span>别名: </span>根岸 まさ子</li><li><span style=\"visibility:hidden;\">别名: </span>ねぎし まさ子</li><li><span style=\"visibility:hidden;\">别名: </span>Negishi Masako</li><li><span>性别: </span>女</li>","detail":"しゅりの親友でクラスメイト。やはりしゅりとは3年間同じクラス。2年、3年とも学級委員長。<br />シニカルな言動でしゅりやめぐみをからかうが二人に対する友情も本物。しゅりに近づく大谷は微妙に敵。<br />朝が弱く、学級委員長であるにも関わらず遅刻してしまうので「学級委員の権限で登校時刻を遅らせられないか」と真剣に考えるほど。<br />しゅりとの付き合いは中学校に入ってから。小学校時代は友達づきあいよりも読書を優先した結果ずっと一人で、中学校に入ってからは「向こうから話しかけてくれれば話題は沢山ある」と思っていたが、たまたましゅりと接したことで「臆病なため自分から『友達になってほしい』と言えなかっただけ」だと気づかされる。<br />兄と姉がいる。兄はクラス担任で、3人がずっと同じクラスなのは他のクラス担任から寄せられるしゅりのトレード要請に対する兄の努力による部分もあるらしい。","jobs":[{"href":"/subject/103085","name":"小森さんは断れない！","nameCn":"小森同学拒绝不了！","cover":"//lain.bgm.tv/pic/cover/g/db/63/103085_ZVeCB.jpg","staff":"主角","cast":"","castHref":"","castTag":"","castCover":"","type":1},{"href":"/subject/138205","name":"小森さんは断れない！","nameCn":"小森同学拒绝不了！","cover":"//lain.bgm.tv/pic/cover/g/c2/2f/138205_xJAP3.jpg","staff":"主角","cast":"長縄まりあ","castHref":"/person/14918","castTag":"CV","castCover":"//lain.bgm.tv/pic/crt/s/5b/8c/14918_prsn_1ZbBH.jpg","type":2},{"href":"/subject/146611","name":"大家さんは思春期！","nameCn":"房东妹子青春期","cover":"//lain.bgm.tv/pic/cover/g/cf/0e/146611_H3rUX.jpg","staff":"客串","cast":"","castHref":"","castTag":"","castCover":"","type":2}]}