{"name":"Yatagarasu","nameCn":"","cover":"//lain.bgm.tv/pic/crt/m/4d/02/11288_prsn_DIzd4.jpg","info":"<li><span>别名: </span>八咫鴉</li><li><span>HP: </span>http://www.yatanootori.com/yatagarasu/main.html</li>","detail":"","works":[{"href":"/subject/58383","name":"異形の鼓動 〜歪なる欲の交わり〜","cover":"//lain.bgm.tv/pic/cover/g/54/22/58383_9yyzm.jpg","staff":"开发"},{"href":"/subject/49321","name":"星彩のレゾナンス / 星彩的共鸣","cover":"//lain.bgm.tv/pic/cover/g/a2/4f/49321_mjt67.jpg","staff":"开发"},{"href":"/subject/224416","name":"～淫蟲和伝 怪蠱録～","cover":"//lain.bgm.tv/pic/cover/g/9d/e9/224416_h81dW.jpg","staff":"开发"},{"href":"/subject/36901","name":"古色迷宮輪舞曲 ～HISTOIRE DE DESTIN～ / 古色迷宫轮舞曲 ～HISTOIRE DE DESTIN～","cover":"//lain.bgm.tv/pic/cover/g/69/a5/36901_Zm215.jpg","staff":"开发"},{"href":"/subject/22971","name":"テンタクルロード -我が手に堕ちよ勇壮なる乙女-","cover":"//lain.bgm.tv/pic/cover/g/f3/11/22971_Yvx3g.jpg","staff":"开发"}]}