{"name":"千葉芙美香","nameCn":"千叶芙美香","cover":"//lain.bgm.tv/pic/crt/m/ef/c8/28070_prsn_x8nSF.jpg","info":"<li><span>简体中文名: </span>千叶芙美香</li><li><span>别名: </span>千葉 芙美香</li><li><span style=\"visibility:hidden;\">别名: </span>ちば ふみか</li><li><span style=\"visibility:hidden;\">别名: </span>Chiba Fumika</li><li><span>性别: </span>女</li><li><span>生日: </span>????-06-06</li><li><span>血型: </span>B</li><li><span>引用来源: </span>upandups.net/actor/chibafumika/</li><li><span>出生地: </span>日本·宫城县</li><li><span>事务所: </span>アップアンドアップス</li><li><span>个人博客: </span>ameblo.jp/love--pome/</li><li><span>Twitter: </span>@1fumika6</li>","detail":"","voices":[{"href":"/character/15146","name":"つくだに","nameCn":"","cover":"//lain.bgm.tv/pic/crt/s/aa/1a/15146_crt_WCZ4C.jpg","subjectHref":"/subject/23537","subjectName":"ポヨポヨ観察日記","subjectNameCn":"嘟嘟猫观察日记","staff":"客串","subjectCover":"//lain.bgm.tv/pic/cover/g/32/4e/23537_deaDg.jpg"},{"href":"/character/15144","name":"山下マキ","nameCn":"","cover":"//lain.bgm.tv/pic/crt/s/32/46/15144_crt_sdsOR.jpg","subjectHref":"/subject/23537","subjectName":"ポヨポヨ観察日記","subjectNameCn":"嘟嘟猫观察日记","staff":"配角","subjectCover":"//lain.bgm.tv/pic/cover/g/32/4e/23537_deaDg.jpg"}]}