{"name":"氷室霧絵","nameCn":"冰室雾绘","cover":"//lain.bgm.tv/pic/crt/m/b6/8e/77793_crt_c3t63.jpg","info":"<li><span>简体中文名: </span>冰室雾绘</li><li><span>别名: </span>ひむろ きりえ</li><li><span>性别: </span>女</li>","detail":"冰室邸最后一代绳之巫女，17岁。<br />自从7岁被选为巫女人选后，冰室家为了让她保持心灵的纯净便将她关在远离尘嚣的冰室邸中养大，连在庭院中散步的日子都加以限制。<br />在祭仪前夕恰逢一名容貌酷似真冬的年轻客人来访冰室邸。初次接触外界来的人的雾绘爱上了他，冰室家当主因而下令将该名男子藏起（即杀死）。仍然猜知心上人死亡的雾绘心情大受打击，导致仪式失败，瘴气泄出。被瘴气感染的雾绘化为怨灵，捕捉所有闯入宅邸的人并让他们体验与自己相同的下场：绳裂至死。但另一方面，雾绘对于自己未能完成仪式十分悔恨，导致分裂出另一个具有孩童长像的自己，并且帮助真冬和深红修复失败的祭仪。","jobs":[{"href":"/subject/1599","name":"零～ZERO～","nameCn":"零-zero","cover":"//lain.bgm.tv/pic/cover/g/83/e8/1599_UC0as.jpg","staff":"配角","cast":"","castHref":"","castTag":"","castCover":""}]}