{"name":"皇鼎","nameCn":"皇鼎","cover":"//lain.bgm.tv/pic/crt/m/5c/f0/19733_crt_vl9Io.jpg","info":"<li><span>简体中文名: </span>皇鼎</li><li><span>别名: </span>皇 鼎</li><li><span style=\"visibility:hidden;\">别名: </span>すめらぎ かなえ</li><li><span style=\"visibility:hidden;\">别名: </span>Sumeragi Kanae</li><li><span>性别: </span>男</li>","detail":"“丑闻”的干部，修身大学文学部的犯罪史学讲座教授，通称“教授”。<br />祝和病院坂姊妹法律上的监护人，在“丑闻”中担任“女王监视官”。<br />本身是个喜欢看权利者们互相残杀的变态，还是个不折不扣的萝莉控。<br />从事犯罪史与犯罪心理的研究，著有《社会不安与群体心理》为首的论文和著作，曾在谈话中提及诺玛‧葛雷兰特。<br />在杀人游戏开始之后就不断向病院坂姊妹提供情报。虽然碍于“丑闻”的规则无法直接介入战斗，但还是会对切提供一定程度上的间接帮助。","jobs":[{"href":"/subject/54705","name":"断裁分離のクライムエッジ","nameCn":"断裁分离的罪恶之剪","cover":"//lain.bgm.tv/pic/cover/g/81/4a/54705_g0zBb.jpg","staff":"配角","cast":"遊佐浩二","castHref":"/person/4614","castTag":"CV","castCover":"//lain.bgm.tv/pic/crt/s/9e/0b/4614_prsn_qQyu9.jpg","type":2}]}