{"name":"依澄れい","nameCn":"","cover":"//lain.bgm.tv/pic/crt/m/fd/d5/19902_prsn_8458c.jpg","info":"<li><span>别名: </span>いづみ れい</li><li><span>生日: </span>4月12日</li><li><span>Twitter: </span>@idumirei</li>","detail":"依澄 れい（いづみ れい、4月12日 -）は、日本の漫画家・イラストレーター。岩手県出身。","works":[{"href":"/subject/240461","name":"はっぴー腐女子 / 快乐腐女子","cover":"//lain.bgm.tv/pic/cover/g/f2/40/240461_2vdfv.jpg","staff":"插图"},{"href":"/subject/18442","name":"true tears ～トゥルーティアーズ～ / 真实之泪","cover":"//lain.bgm.tv/pic/cover/g/ed/2f/18442_623dv.jpg","staff":"原画"},{"href":"/subject/149887","name":"ぽすたるWORK","cover":"//lain.bgm.tv/pic/cover/g/97/b5/149887_jp.jpg","staff":"作者"},{"href":"/subject/28814","name":".hack//黄昏の腕輪伝説 / .hack//黄昏的腕轮传说","cover":"//lain.bgm.tv/pic/cover/g/f9/02/28814_k5f0J.jpg","staff":"作画"},{"href":"/subject/187323","name":"卓球場シリーズ / 台球场系列","cover":"//lain.bgm.tv/pic/cover/g/32/fc/187323_17Kvw.jpg","staff":"插图"}]}