{"name":"小野寺小咲","nameCn":"小野寺小咲","cover":"//lain.bgm.tv/pic/crt/m/e9/f1/16703_crt_z3L5y.jpg","info":"<li><span>简体中文名: </span>小野寺小咲</li><li><span>别名: </span>Kosaki Onodera</li><li><span style=\"visibility:hidden;\">别名: </span>おのでら こさき</li><li><span style=\"visibility:hidden;\">别名: </span>Onodera Kosaki</li><li><span>性别: </span>女</li><li><span>生日: </span>6月15日</li><li><span>血型: </span>O型</li><li><span>身高: </span>157cm</li><li><span>体重: </span>43kg</li><li><span>引用来源: </span>wikipedia</li>","detail":"本作のヒロイン。楽と千棘のクラスメイト。黒髪で、アシンメトリーな髪型も特徴である。実家は和菓子屋「おのでら」を経営している。<br />中学の頃から楽に好意を寄せているが恋愛に対しては奥手で、言い出せないままでいる。実は両想いの上、舞子集や宮本るり等の互いの親しい友人から見てもそれがまるわかりなのだが互いの性格のせいで関係が発展しないままでいる。鍵を持っていて、小さい頃に会った思い出の男の子がいるらしい。<br />他人を気遣う優しさを持っていて、クラス内での男子の人気も高い。料理の腕は、小咲の母曰く「仕上げ以外死ぬほど下手くそ」。","jobs":[{"href":"/subject/90623","name":"ニセコイ マジコレ！？","nameCn":"伪恋：真的吗!?","cover":"//lain.bgm.tv/pic/cover/g/65/5e/90623_jZ3oj.jpg","staff":"主角","cast":"花澤香菜","castHref":"/person/4765","castTag":"CV","castCover":"//lain.bgm.tv/pic/crt/s/ae/ff/4765_prsn_67Kc7.jpg","type":4},{"href":"/subject/111298","name":"想像ダイアリー","nameCn":"","cover":"//lain.bgm.tv/pic/cover/g/8e/11/111298_L6LsW.jpg","staff":"主角","cast":"","castHref":"","castTag":"","castCover":"","type":3},{"href":"/subject/112464","name":"大切の作り方","nameCn":"","cover":"//lain.bgm.tv/pic/cover/g/2e/90/112464_9klTy.jpg","staff":"主角","cast":"","castHref":"","castTag":"","castCover":"","type":3},{"href":"/subject/124428","name":"ホワイトギフト","nameCn":"","cover":"//lain.bgm.tv/pic/cover/g/f3/3c/124428_icZHZ.jpg","staff":"主角","cast":"","castHref":"","castTag":"","castCover":"","type":3},{"href":"/subject/74628","name":"ニセコイ","nameCn":"伪恋","cover":"//lain.bgm.tv/pic/cover/g/98/71/74628_8HHlL.jpg","staff":"主角","cast":"花澤香菜","castHref":"/person/4765","castTag":"CV","castCover":"//lain.bgm.tv/pic/crt/s/ae/ff/4765_prsn_67Kc7.jpg","type":2},{"href":"/subject/104196","name":"ニセコイ OAD","nameCn":"伪恋 OAD","cover":"//lain.bgm.tv/pic/cover/g/2d/bb/104196_mIzDE.jpg","staff":"主角","cast":"花澤香菜","castHref":"/person/4765","castTag":"CV","castCover":"//lain.bgm.tv/pic/crt/s/ae/ff/4765_prsn_67Kc7.jpg","type":2},{"href":"/subject/35987","name":"ニセコイ","nameCn":"伪恋","cover":"//lain.bgm.tv/pic/cover/g/97/b1/35987_k5kmV.jpg","staff":"主角","cast":"","castHref":"","castTag":"","castCover":"","type":1},{"href":"/subject/131813","name":"曖昧ヘルツ / TrIGgER","nameCn":"","cover":"//lain.bgm.tv/pic/cover/g/d7/05/131813_3Xzj3.jpg","staff":"主角","cast":"","castHref":"","castTag":"","castCover":"","type":3},{"href":"/subject/114758","name":"ニセコイ:","nameCn":"伪恋：","cover":"//lain.bgm.tv/pic/cover/g/22/cd/114758_27XTt.jpg","staff":"主角","cast":"花澤香菜","castHref":"/person/4765","castTag":"CV","castCover":"//lain.bgm.tv/pic/crt/s/ae/ff/4765_prsn_67Kc7.jpg","type":2},{"href":"/subject/144839","name":"merchen ticktack / マジカル☆スタイリング","nameCn":"","cover":"//lain.bgm.tv/pic/cover/g/2d/3c/144839_Z8QJR.jpg","staff":"主角","cast":"","castHref":"","castTag":"","castCover":"","type":3},{"href":"/subject/151930","name":"クレヨンカバー","nameCn":"","cover":"//lain.bgm.tv/pic/cover/g/37/56/151930_XjkMO.jpg","staff":"主角","cast":"","castHref":"","castTag":"","castCover":"","type":3},{"href":"/subject/100913","name":"リカバーデコレーション","nameCn":"","cover":"//lain.bgm.tv/pic/cover/g/84/71/100913_X7L7L.jpg","staff":"主角","cast":"","castHref":"","castTag":"","castCover":"","type":3},{"href":"/subject/124743","name":"NISEKOI BEST SONGS","nameCn":"","cover":"//lain.bgm.tv/pic/cover/g/a3/4e/124743_dd7I1.jpg","staff":"主角","cast":"","castHref":"","castTag":"","castCover":"","type":3},{"href":"/subject/89018","name":"本命アンサー","nameCn":"","cover":"//lain.bgm.tv/pic/cover/g/66/74/89018_ufggg.jpg","staff":"主角","cast":"","castHref":"","castTag":"","castCover":"","type":3}]}