{"name":"アネーシャ・オル・メガーラ","nameCn":"","cover":"//lain.bgm.tv/pic/crt/m/c4/41/4700_crt_anidb.jpg","info":"<li><span>性别: </span>女</li><li><span>别名: </span>アネーシャ・オル・メガーラ</li><li><span style=\"visibility:hidden;\">别名: </span>Aneasha Ol Megarla</li><li><span>引用来源: </span>anidb.net</li>","detail":"","jobs":[{"href":"/subject/1967","name":"ヒロイック・エイジ","nameCn":"英雄时代","cover":"//lain.bgm.tv/pic/cover/g/a8/2d/1967_EE8zY.jpg","staff":"配角","cast":"清水香里","castHref":"/person/3838","castTag":"CV","castCover":"//lain.bgm.tv/pic/crt/s/f2/6d/3838_seiyu_anidb.jpg"}]}