{"name":"ジョン","nameCn":"约翰","cover":"//lain.bgm.tv/pic/crt/m/c9/06/22301_crt_00z9D.jpg","info":"<li><span>简体中文名: </span>约翰</li><li><span>别名: </span>John</li><li><span>性别: </span>男</li>","detail":"在敦子赴任的南翠学园留学的学生。转入了和ゆい一样的班级。<br />体型健壮，筋肉男。<br />因为语言和生活习惯等不熟悉的事情有很多，所以ゆい负责照顾他直到熟悉为止。<br /><br />喜欢外表年幼的女孩子，口头上说是亲密接触而总是纠缠着万分厌恶的ゆい。<br />但是事态慢慢地扩大……<br /><br />癖好：喜欢小女生。","jobs":[{"href":"/subject/81748","name":"町ぐるみの罠〜白濁にまみれた肢体〜","nameCn":"","cover":"//lain.bgm.tv/pic/cover/g/22/ed/81748_KA1LF.jpg","staff":"配角","cast":"","castHref":"","castTag":"","castCover":"","type":4},{"href":"/subject/48736","name":"町ぐるみの罠～白濁にまみれた肢体～","nameCn":"","cover":"//lain.bgm.tv/pic/cover/g/29/33/48736_3g0e9.jpg","staff":"配角","cast":"","castHref":"","castTag":"","castCover":"","type":2}]}