{"name":"紫女","nameCn":"紫女","cover":"//lain.bgm.tv/pic/crt/m/3f/f5/86069_crt_Xzv95.jpg","info":"<li><span>简体中文名: </span>紫女</li><li><span>性别: </span>女</li>","detail":"紫兰轩女主人、流沙创立者之一。<br />紫发紫衣的成熟女子，妩媚并富有女人味，是韩国著名花街柳巷“紫兰轩”的主人。与琴姬弄玉以姐妹相称。武艺高强，轻功也很厉害，并极擅策术，能够轻易洞察人心。同时精通调香、易容、药理，冶炼之术及制毒用毒之术，紫兰轩以风月之地作为掩饰，收集着韩国乃至六国的重要情报，成为当时著名的地下情报屋，且暗中培养了一群身怀绝技的女刺客。","jobs":[{"href":"/subject/127448","name":"天行九歌","nameCn":"天行九歌","cover":"//lain.bgm.tv/pic/cover/g/62/cc/127448_y9J7c.jpg","staff":"主角","cast":"黄莺","castHref":"/person/39645","castTag":"CV","castCover":"//lain.bgm.tv/pic/crt/s/30/e6/39645_prsn_5dQP3.jpg","type":2},{"href":"/subject/281240","name":"天行九歌 第二部分","nameCn":"","cover":"//lain.bgm.tv/pic/cover/g/e8/cb/281240_3E877.jpg","staff":"主角","cast":"黄莺","castHref":"/person/39645","castTag":"CV","castCover":"//lain.bgm.tv/pic/crt/s/30/e6/39645_prsn_5dQP3.jpg","type":2},{"href":"/subject/17045","name":"秦时明月之万里长城","nameCn":"秦时明月之万里长城","cover":"//lain.bgm.tv/pic/cover/g/82/95/17045_owkaA.jpg","staff":"配角","cast":"黄莺","castHref":"/person/39645","castTag":"CV","castCover":"//lain.bgm.tv/pic/crt/s/30/e6/39645_prsn_5dQP3.jpg","type":2},{"href":"/subject/105592","name":"空山鸟语","nameCn":"天行九歌之空山鸟语","cover":"//lain.bgm.tv/pic/cover/g/5e/32/105592_AX61v.jpg","staff":"客串","cast":"黄莺","castHref":"/person/39645","castTag":"CV","castCover":"//lain.bgm.tv/pic/crt/s/30/e6/39645_prsn_5dQP3.jpg","type":2}]}