{"name":"川村賢一","nameCn":"川村贤一","cover":"","info":"<li><span>简体中文名: </span>川村贤一</li><li><span>别名: </span>川村 賢一</li><li><span style=\"visibility:hidden;\">别名: </span>かわむら けんいち</li><li><span style=\"visibility:hidden;\">别名: </span>Kawamura Kenichi</li><li><span>性别: </span>男</li>","detail":"","works":[{"href":"/subject/261805","name":"Re:ゼロから始める異世界生活 氷結の絆 / Re：从零开始的异世界生活 冰结之绊","cover":"//lain.bgm.tv/pic/cover/g/29/f6/261805_0XD0Z.jpg","staff":"系列监督"},{"href":"/subject/279457","name":"ソードアート・オンライン アリシゼーション War of Underworld / 刀剑神域 Alicization篇 War of Underworld","cover":"//lain.bgm.tv/pic/cover/g/dd/a6/279457_2p2B9.jpg","staff":"分镜"},{"href":"/subject/226256","name":"賢者の孫 / 贤者之孙","cover":"//lain.bgm.tv/pic/cover/g/dc/81/226256_dZdQ2.jpg","staff":"分镜"},{"href":"/subject/263756","name":"マーベル フューチャー・アベンジャーズ2 / 漫威未来复仇者 第二季","cover":"//lain.bgm.tv/pic/cover/g/c3/be/263756_zwiRn.jpg","staff":"分镜"},{"href":"/subject/129807","name":"シュタインズ・ゲート ゼロ / 命运石之门 0","cover":"//lain.bgm.tv/pic/cover/g/f6/91/129807_9VAi4.jpg","staff":"OP・ED 分镜"}]}