{"name":"曽和まどか","nameCn":"曽和园香","cover":"//lain.bgm.tv/pic/crt/m/42/de/10039_prsn_OI7qR.jpg","info":"<li><span>简体中文名: </span>曽和园香</li>","detail":"","voices":[{"href":"/character/19672","name":"内海ゆきな","nameCn":"内海友里奈","cover":"//lain.bgm.tv/pic/crt/s/7f/3b/19672_crt_SYmV8.jpg","subjectHref":"/subject/60491","subjectName":"宮河家の空腹","subjectNameCn":"宫河家的空腹","staff":"配角","subjectCover":"//lain.bgm.tv/pic/cover/g/db/6e/60491_3en3E.jpg"}],"works":[{"href":"/subject/93346","name":"「宮河家の空腹」特製CD","cover":"//lain.bgm.tv/pic/cover/g/bd/16/93346_2tnxE.jpg","staff":"艺术家"},{"href":"/subject/89581","name":"TVアニメ 勇者になれなかった俺はしぶしぶ就職を決意しました。キャラクターソング エキストラレボリューション","cover":"//lain.bgm.tv/pic/cover/g/d5/61/89581_855AG.jpg","staff":"艺术家"}]}