{"name":"腾讯动漫","nameCn":"腾讯网动漫频道","cover":"//lain.bgm.tv/pic/crt/m/f8/1d/19120_prsn_IGgP9.jpg","info":"<li><span>简体中文名: </span>腾讯网动漫频道</li>","detail":"腾讯网动漫频道，是腾讯旗下的国内动漫综合网站。拥有专业的动漫资讯、动漫论坛、漫画家微博。腾讯动漫原创漫画、正版动漫平台，为动漫迷带来正版时代。同时提供二次元最新动态，覆盖国内外动漫盛典时讯、一线动漫名家圈子零距离接触。<br /><br />腾讯动漫独家引入的漫画作品包括《火影忍者》、《航海王》、《龙珠》、《阿拉蕾》、《圣斗士星矢》、《银魂》、《游戏王》、《网球王子》、《家庭教师》、《境·界》及《爆漫王》。<br />此次合作是集英社首次在中国授权漫画电子版权，也是国内动漫行业较大规模的一次版权交易。","works":[{"href":"/subject/242739","name":"秦侠 / 秦侠","cover":"//lain.bgm.tv/pic/cover/g/3a/84/242739_Xox6W.jpg","staff":"企画"},{"href":"/subject/282635","name":"狐妖小红娘 金晨曦篇 / 狐妖小红娘 金晨曦篇","cover":"//lain.bgm.tv/pic/cover/g/4c/9e/282635_HuU91.jpg","staff":"企画"},{"href":"/subject/285784","name":"一人之下3·入世篇 / 一人之下3·入世篇","cover":"//lain.bgm.tv/pic/cover/g/9d/c6/285784_4zJ4J.jpg","staff":"企画"},{"href":"/subject/291212","name":"麻辣女配 / 麻辣女配","cover":"//lain.bgm.tv/pic/cover/g/ae/95/291212_t0kt0.jpg","staff":"企画"},{"href":"/subject/242745","name":"妖精种植手册 / 妖精种植手册","cover":"//lain.bgm.tv/pic/cover/g/19/98/242745_nXP7R.jpg","staff":"企画"}]}