{"name":"吉野葉平","nameCn":"吉野叶平","cover":"//lain.bgm.tv/pic/crt/m/7d/67/54950_crt_tutZu.jpg","info":"<li><span>简体中文名: </span>吉野叶平</li><li><span>别名: </span>吉野 葉平</li><li><span style=\"visibility:hidden;\">别名: </span>よしの ようへい</li><li><span style=\"visibility:hidden;\">别名: </span>yoshino youhei</li><li><span>性别: </span>男</li>","detail":"本作の主人公。あずみとは恋人同士。プライベートでは「あずみ」と呼んでるが、学校では「あずみ先輩」と呼んでいる。クラリネット担当。あずみが吹奏楽部を引退した後は部長に就任した。","jobs":[{"href":"/subject/44484","name":"7時間目の音符","nameCn":"7时间目的音符","cover":"//lain.bgm.tv/pic/cover/g/52/34/44484_x94Jk.jpg","staff":"主角","cast":"","castHref":"","castTag":"","castCover":"","type":1}]}