{"name":"陈红","nameCn":"陈红","cover":"//lain.bgm.tv/pic/crt/m/8c/08/16532_prsn_5jOok.jpg","info":"<li><span>简体中文名: </span>陈红</li><li><span>性别: </span>女</li><li><span>生日: </span>1968年12月20日</li><li><span>血型: </span>O型</li><li><span>身高: </span>166cm</li><li><span>出生地: </span>中国江西省上饶市</li><li><span>教育程度: </span>上海戏剧学院表演系 大学本科</li><li><span>亲属: </span>（夫）陈凯歌，（子）陈雨昂，（子）陈飞宇</li><li><span>活跃年代: </span>1993年-</li><li><span>经纪公司: </span>文化传媒公司</li>","detail":"陈红，1968年12月13日出生于江西省上饶市，毕业于上海戏剧学院表演系，中国内地著名女演员、制片人，被誉为中国影视界“最美名”女演员，同时也是中国第一代“琼瑶女郎”。<br />1985年，参演个人首部电影《这里有泉水》，饰演余多正式出道。1989年，参演电视剧《红楼梦》，饰演紫鹃。1991年，参演电视剧《三国演义》，饰演貂蝉。1993年，参演电视剧《梅花三弄》，饰演汪子璇。1998年，参演电视剧《大明宫词》，饰演太平公主。<br />1996年，陈红和陈凯歌导演在美国注册结婚。婚后陈红渐渐从台前准入幕后，由她担任总制片的电影有《无极》、《梅兰芳》 、《赵氏孤儿》等，电视剧有《吕布与貂蝉》、《和你在一起》等。其中，影片《搜索》打破了当时国产文艺片最高票房纪录，成为新一任的国产文艺片票房之王。","works":[{"href":"/subject/228511","name":"妖猫传 / 妖猫传","cover":"//lain.bgm.tv/pic/cover/g/29/2a/228511_n9v78.jpg","staff":"制片人/制作人"},{"href":"/subject/123230","name":"大明宫词","cover":"//lain.bgm.tv/pic/cover/g/9d/e5/123230_8eQ7B.jpg","staff":"主演"},{"href":"/subject/123394","name":"春光灿烂猪八戒","cover":"//lain.bgm.tv/pic/cover/g/fb/41/123394_X9DlW.jpg","staff":"主演"},{"href":"/subject/123262","name":"神鵰俠侶 (1998 台灣) / 神雕侠侣","cover":"//lain.bgm.tv/pic/cover/g/dd/3d/123262_6DAe5.jpg","staff":"配角"},{"href":"/subject/123218","name":"三国演义 (1994)","cover":"//lain.bgm.tv/pic/cover/g/e9/7a/123218_2HpT2.jpg","staff":"配角"}]}