{"name":"アトリエかぐや","nameCn":"Atelier KAGUYA","cover":"//lain.bgm.tv/pic/crt/m/92/c6/2346_prsn_nJ92K.jpg","info":"<li><span>简体中文名: </span>Atelier KAGUYA</li><li><span>别名: </span>株式会社アステックトゥーワン</li><li><span style=\"visibility:hidden;\">别名: </span>Atelier Kaguya</li><li><span style=\"visibility:hidden;\">别名: </span>竹子社</li><li><span>Website: </span>www.a-kaguya.com/top.html</li><li><span>公司地址: </span>大阪市西区九条南2-16-8ASTECビル</li>","detail":"株式会社アステックトゥーワン（大阪市西区九条南2-16-8ASTECビル）のアダルトゲームブランドである。発売日の延期やバグの存在などアダルトゲームで多発する問題が少ないことや、安定した内容から人気の高いブランドの1つである。<br /><br />keyに代表される「泣きゲー」とは正反対のエロティズムを重視した作品（いわゆる「抜きゲー」）を多数発売しており、どの作品においても、密度の濃いセックスシーンが多数挿入されている。Berkshire Yorkshireからは、『家庭教師のおねえさん』や『姉汁』等、いわゆる「お姉さん」に特化した作品を発売している。また、卑語を修正するピー音が非常に短く、消すべき音と微妙にずれていることによる「修正されているのに聴き取れる卑語（いわゆるかぐや消し）」を用いたメーカーの先駆けともなっている。<br /><br />それぞれ堅調な売り上げを維持している一方で、抜きゲーメーカーの壁である3万本を越えるような爆発的なヒット作は生み出せていない。<br /><br />2010年から2011年にかけ、これまでの堅調な売り上げに貢献していた看板原画家のchoco chipやM&amp;Mが相次いで退社・移籍したため、それ以降は一時期ロープライス作品に比重を置いていた。また、2011年からは『KAGUYAコレクション』と題して過去作品の廉価版のパッケージ販売やダウンロード販売も行っている。","works":[{"href":"/subject/310158","name":"Mama×Holic～魅惑のママと甘々カンケイ～","cover":"//lain.bgm.tv/pic/cover/g/f1/07/310158_rxGdG.jpg","staff":"开发"},{"href":"/subject/304722","name":"搾精士のお姉さん ～女性だけの街で精液奴○にされちゃった僕～","cover":"/img/no_icon_subject.png","staff":"开发"},{"href":"/subject/290678","name":"ままごと～ママとないしょのエッチしましょ～","cover":"/img/no_icon_subject.png","staff":"开发"},{"href":"/subject/289860","name":"ラブホリック～魅惑の乙女と白濁カンケイ～ THE ANIMATION","cover":"/img/no_icon_subject.png","staff":"原作"},{"href":"/subject/285132","name":"しごカレ ～エッチな女子大生とドキ×2ラブレッスン!! THE ANIMATION","cover":"/img/no_icon_subject.png","staff":"原作"}]}