{"name":"ヴラディレーナ・ミリーゼ","nameCn":"弗拉迪蕾娜·米丽洁","cover":"//lain.bgm.tv/pic/crt/m/18/cd/57715_crt_pJZxr.jpg","info":"<li><span>简体中文名: </span>弗拉迪蕾娜·米丽洁</li><li><span>别名: </span>レーナ</li><li><span style=\"visibility:hidden;\">别名: </span>蕾娜</li><li><span style=\"visibility:hidden;\">别名: </span>Vladilena Mirizé</li><li><span>性别: </span>女</li><li><span>引用来源: </span>http://dengekitaisho.jp/special/23/eighty-six/</li>","detail":"共和国成立以前からこの地に住む白系種（アルバ）であり、かつ貴種として知られる白銀種（セレナ）の血を純血で受け継ぐ名家・ミリーゼ家の才媛。<br />弱冠16歳で共和国軍の少佐にまで上り詰めたエリートで、ギアーデ帝国の〈レギオン〉部隊と最前線で戦うエイティシックスの指揮管制官〈ハンドラー〉としての職務に当たることとなった。<br />その才能が上官の目に止まり、東部戦線第一戦区第一防衛戦隊、通称〈スピアヘッド〉戦隊へ配属。そこでシンと出会う。","jobs":[{"href":"/subject/219247","name":"86―エイティシックス―","nameCn":"86―不存在的战区―","cover":"//lain.bgm.tv/pic/cover/g/0d/a0/219247_LLYCa.jpg","staff":"主角","cast":"","castHref":"","castTag":"","castCover":"","type":1},{"href":"/subject/219249","name":"86―エイティシックス―","nameCn":"86- Eighty Six-","cover":"//lain.bgm.tv/pic/cover/g/e6/e4/219249_bpuR8.jpg","staff":"主角","cast":"","castHref":"","castTag":"","castCover":"","type":1},{"href":"/subject/302189","name":"86―エイティシックス―","nameCn":"86 -不存在的地域-","cover":"//lain.bgm.tv/pic/cover/g/a4/b3/302189_Q1fXx.jpg","staff":"主角","cast":"長谷川育美","castHref":"/person/30858","castTag":"CV","castCover":"//lain.bgm.tv/pic/crt/s/85/45/30858_prsn_tXT84.jpg","type":2}]}