{"name":"兵頭一歩","nameCn":"兵头一步","cover":"//lain.bgm.tv/pic/crt/m/07/2b/2943_prsn_jgfJ1.jpg","info":"<li><span>简体中文名: </span>兵头一步</li><li><span>别名: </span>ひょうどうかずほ</li><li><span style=\"visibility:hidden;\">别名: </span>Hyoudou Kazuho</li><li><span>性别: </span>男</li><li><span>引用来源: </span>wikipedia</li>","detail":"大阪府出身の男性アニメ脚本家、ライトノベル作家。現在フリー。<br /><br />以前はサンライズで制作進行の仕事をしていた。『勇者王ガオガイガー』では、担当した話に「兵頭一歩」というキャラクターまで登場。","works":[{"href":"/subject/319802","name":"キラッとプリ☆チャン♪ソングコレクション ~ from MELODY FANTASY ~","cover":"//lain.bgm.tv/pic/cover/g/66/a6/319802_t0ydh.jpg","staff":"作词"},{"href":"/subject/319803","name":"キラッとプリ☆チャン♪ソングコレクション ~ from OCEAN MERMAID ~","cover":"//lain.bgm.tv/pic/cover/g/aa/ae/319803_OgOKG.jpg","staff":"作词"},{"href":"/subject/319801","name":"キラッとプリ☆チャン♪ソングコレクション ~ from RAINBOW SKY ~","cover":"//lain.bgm.tv/pic/cover/g/9e/b9/319801_F2E21.jpg","staff":"作词"},{"href":"/subject/301541","name":"トニカクカワイイ / 总之就是非常可爱","cover":"//lain.bgm.tv/pic/cover/g/66/50/301541_p2z4K.jpg","staff":"系列构成"}]}