{"name":"綾瀬はるか","nameCn":"绫濑遥","cover":"//lain.bgm.tv/pic/crt/m/1c/2b/7132_prsn_vrpwf.jpg","info":"<li><span>简体中文名: </span>绫濑遥</li><li><span>别名: </span>綾瀬 はるか</li><li><span style=\"visibility:hidden;\">别名: </span>あやせ はるか</li><li><span style=\"visibility:hidden;\">别名: </span>Ayase Haruka</li><li><span style=\"visibility:hidden;\">别名: </span>蓼丸 綾（たでまる あや）</li><li><span>性别: </span>女</li><li><span>生日: </span>1985年3月24日</li><li><span>血型: </span>B</li><li><span>身高: </span>165cm</li><li><span>BWH: </span>B88 W61 H91</li><li><span>引用来源: </span>wiki</li>","detail":"日本广岛县出身的女演员和女歌手。帝京大学短期大学国际沟通学科中途退学，现隶属Horipro事务所。身高165cm，血型B型。<br />从广岛县立祇园北高等学校转到堀越高等学校毕业，于帝京大学短期大学中途退学。<br />2000年，获得第25回HORIPRO TALENT SCOUT CARAVAN GRAND PRIX特别奖，当时以本名“蓼丸绫”参选。从此成为Horipro旗下艺人。<br />2001年，在NTV电视台播放的电视剧《金田一少年之事件簿III》中作为女演员初次亮相。<br />2004年，《在世界中心呼唤爱》电视剧中饰演广濑亚纪，一炮而红。<br />2006年，邀请到音乐制作人小林武史担任监制，进军歌坛，于3月24日推出首张单曲《Period》。<br />2008年，继《JUSTICE》、《帅哥医生》之后，与同门师兄妻夫木聪第三度合作，出演喜剧大师三谷幸喜执导的电影《魔幻时刻》，这也是三谷导演首次同时选用两名年轻演员担任重要角色。同年主演电影《我的女友是机器人》、《女座头市》获第21回日刊体育电影大赏主演女优赏。<br />2011年，NHK公布2013年大河剧《八重之樱》，由绫濑遥担当主演日本教育家新岛襄妻子新岛八重的一生，也是首次出演NHK戏剧演出。<br />2013年，由于出演大河剧表现优异，以及NHK东日本大震灾灾后复兴访视计划《我回来了，东北》亲民形象深植人心，正式担任年度除夕节目第64回NHK红白歌合战红组主持人（是2006年后再度起用大河剧女主角）。同时也应邀于中场休息前和红白歌手大合唱震灾复兴主题曲《花正在开》，是在第48回（1997年）以后红白两组主持人有演唱记录。<br />2015年，出演作品《海街日记》是第68届戛纳影展的竞赛片之一，但并没有获奖。","voices":[{"href":"/character/27124","name":"遥","nameCn":"","cover":"//lain.bgm.tv/pic/crt/s/f1/64/27124_crt_0m9Ed.jpg","subjectHref":"/subject/5087","subjectName":"ホッタラケの島 〜遥と魔法の鏡〜","subjectNameCn":"弃宝之岛：遥与魔法镜","staff":"主角","subjectCover":"//lain.bgm.tv/pic/cover/g/04/3c/5087_tc69S.jpg"}],"works":[{"href":"/subject/212426","name":"いだてん～東京オリムピック噺～ / 韦驮天：东京奥运物语","cover":"//lain.bgm.tv/pic/cover/g/84/97/212426_RZrRm.jpg","staff":"配角"},{"href":"/subject/245130","name":"義母と娘のブルース / 继母与女儿的蓝调","cover":"//lain.bgm.tv/pic/cover/g/11/95/245130_Tfzrz.jpg","staff":"主演"},{"href":"/subject/240253","name":"今夜、ロマンス劇場で / 今夜在浪漫剧场","cover":"//lain.bgm.tv/pic/cover/g/af/e1/240253_hSsb7.jpg","staff":"主演"},{"href":"/subject/222399","name":"奥様は、取り扱い注意 / 太太请小心轻放","cover":"//lain.bgm.tv/pic/cover/g/bc/78/222399_fH1qf.jpg","staff":"主演"},{"href":"/subject/227266","name":"本能寺ホテル / 本能寺酒店","cover":"//lain.bgm.tv/pic/cover/g/9e/d3/227266_R3Y3h.jpg","staff":"主演"}]}