{"name":"可可豆动画","nameCn":"成都可可豆动画影视有限公司","cover":"//lain.bgm.tv/pic/crt/m/8f/73/35129_prsn_6H2jp.jpg","info":"<li><span>简体中文名: </span>成都可可豆动画影视有限公司</li><li><span>别名: </span>Chengdu Coco Cartoon Co.,Ltd.</li><li><span>地址: </span>成都高新区天府大道北段28号茂业中心C2207</li><li><span>Weibo: </span>http://weibo.com/cococartoon</li><li><span>Tel: </span>028-86136716</li><li><span>Website: </span>http://www.cococartoon.com/</li>","detail":"成都可可豆动画影视有限公司（Chengdu Coco Cartoon Co.,Ltd.）的前身是国内知名的原创动画团队“饺克力动画工作室”。作为中国原创动漫新生力量，“可可豆动画”是一家专注于高品质原创三维动画电影创作的影视类公司。<br /><br />团队早在2009年就被国家文化部评为&quot;2009年原创动漫扶持企业&quot;；2012年被国家文化部列入&quot;2012年国家动漫品牌建设和保护计划&quot;的名单；同年被四川省政府列为首批重点培育企业。<br /><br />公司的原创动画作品《打，打个大西瓜》(英文名See Through)以及与优酷网联合出品的3D动画微电影《老板的女人》以及《2014南京青奥会口号宣传动画》都得到了业界和广大网友的一致好评！<br /><br />2015年，公司与北京光线影业达成战略合作，公司成为光线“彩条屋影业”旗下公司。将共同打造原创三维动画电影项目《哪吒降世》（暂定名），我们将为中国动画之崛起而努力！","works":[{"href":"/subject/231261","name":"哪吒之魔童降世","cover":"//lain.bgm.tv/pic/cover/g/b9/4e/231261_Ae9qE.jpg","staff":"动画制作"},{"href":"/subject/5919","name":"打，打个大西瓜 / 打，打个大西瓜","cover":"//lain.bgm.tv/pic/cover/g/cd/75/5919_LBh3I.jpg","staff":"制作"}]}